dfjoinseries/README.MD
dfjoinseries/__init__.py
dfjoinseries/requirements.txt
dfjoinseries/thirdparty.json
dfjoinseries-0.10.dist-info/LICENSE.rst
dfjoinseries-0.10.dist-info/METADATA
dfjoinseries-0.10.dist-info/WHEEL
dfjoinseries-0.10.dist-info/top_level.txt
dfjoinseries-0.10.dist-info/RECORD
