Metadata-Version: 2.1
Name: dfjoinseries
Version: 0.10
Summary: Like numpy.char.join for DataFrames
Home-page: https://github.com/hansalemaos/dfjoinseries
Author: Johannes Fischer
Author-email: aulasparticularesdealemaosp@gmail.com
License: MIT
Keywords: join,DataFrames
Classifier: Development Status :: 4 - Beta
Classifier: Programming Language :: Python :: 3 :: Only
Classifier: Programming Language :: Python :: 3.10
Classifier: Topic :: Software Development :: Libraries :: Python Modules
Classifier: Topic :: Utilities
License-File: LICENSE.rst
Requires-Dist: numpy
Requires-Dist: pandas
